hre_tools-0.1.1.dist-info/METADATA
hre_tools-0.1.1.dist-info/WHEEL
hre.libs/libcrypto-f12d9946.so.3
hre.libs/libpoppler-b2b75c1a.so.126
hre.libs/libplc4-e1f9c8d5.so
hre.libs/libplds4-74cf29f1.so
hre.libs/libdeflate-7a207818.so.0
hre.libs/libssl-4a764d83.so.3
hre.libs/libcairo-207b61c5.so.2
hre.libs/liblcms2-7826c295.so.2
hre.libs/libpcre2-8-19c62625.so.0
hre.libs/libnss3-2109f60d.so
hre.libs/libfontconfig-eba9fe88.so.1
hre.libs/libfreetype-5c691e22.so.6
hre.libs/libsmime3-10b11d2f.so
hre.libs/libnspr4-d7ddad6e.so
hre.libs/libbrotlicommon-d0dd623a.so.1
hre.libs/libXau-833aa73c.so.6
hre.libs/libmd-9e8462f7.so.0
hre.libs/libjbig-92f86d0b.so.0
hre.libs/libzstd-37412b7a.so.1
hre.libs/libgmodule-2-17987bf4.0.so.0
hre.libs/libtiff-8a2b1ded.so.6
hre.libs/libmount-70c1da7f.so.1
hre.libs/libblkid-cc3d6ca9.so.1
hre.libs/libwebp-4fedb320.so.7
hre.libs/libnssutil3-5081c2a2.so
hre.libs/libxcb-shm-ce4b516a.so.0
hre.libs/libxcb-35e21829.so.1
hre.libs/libpoppler-glib-562b3181.so.8
hre.libs/libjpeg-dad87949.so.62
hre.libs/liblzma-aaead752.so.5
hre.libs/libffi-983e72b7.so.8
hre.libs/libopenjp2-61474a25.so.7
hre.libs/libpng16-6f34e8ab.so.16
hre.libs/libgio-2-c1b2bc72.0.so.0
hre.libs/libbrotlidec-928b2613.so.1
hre.libs/libpixman-1-cbbdbb3a.so.0
hre.libs/libxcb-render-e2b5e78b.so.0
hre.libs/libbsd-c34693b2.so.0
hre.libs/libXdmcp-911ecd1c.so.6
hre.libs/libselinux-0207e490.so.1
hre.libs/libLerc-6b465f54.so.4
hre/__init__.py
hre/hre.cpython-310-x86_64-linux-gnu.so
hre_tools-0.1.1.dist-info/RECORD
