Metadata-Version: 2.1
Name: hre-tools
Version: 0.1.1
Classifier: Programming Language :: Python :: 3
Classifier: Programming Language :: Python :: 3.7
Classifier: Programming Language :: Python :: 3.8
Classifier: Programming Language :: Python :: 3.9
Classifier: Programming Language :: Python :: 3.10
Classifier: Programming Language :: Python :: 3.11
Classifier: Programming Language :: Rust
Classifier: License :: OSI Approved :: MIT License
Classifier: Operating System :: OS Independent
Summary: A blazing-fast lightweight Rust hybrid retriever optimized for Real Time search.
Author-email: Jared Peck <jared7peck@gmail.com>
License: MIT
Requires-Python: >=3.7
Project-URL: repository, https://github.com/Jmp13033/hre
